{
  "major": "BEPP: Public Pol Anlys BSB",
  "school": "Kelley School of Business",
  "year": 3,
  "total_credits": 30,
  "terms": {
    "fall": {
      "required_completion": "Year 3, Fall",
      "total_credits": 15,
      "courses": [
        {
          "requirement_name": "Integrated Core (I-Core)",
          "critical": true,
          "credits": 12,
          "fulfilling_courses": [
            {
              "course_code": "BUS-BE 375",
              "course_name": "I-CORE F370/M370/P370/Z370",
              "credits": 12,
              "scheduled_terms": ["Spring 2026", "Summer 2026"],
              "note": "Includes Finance, Marketing, Operations, and Leadership components"
            }
          ]
        },
        {
          "requirement_name": "Supplemental Credits for Graduation",
          "critical": false,
          "credits": 3,
          "fulfilling_courses": [],
          "note": "Additional credits needed for graduation can be used to explore interests, including a minor or co-major/second major"
        }
      ]
    },
    "spring": {
      "required_completion": "Year 3, Spring",
      "total_credits": 15,
      "courses": [
        {
          "requirement_name": "Game Theory for Business Strategy",
          "critical": false,
          "credits": 3,
          "fulfilling_courses": [
            {
              "course_code": "BUS-G 303",
              "course_name": "GAME THEORY FOR BUSINESS STRATEGY",
              "credits": 3,
              "scheduled_terms": ["Fall 2025", "Spring 2026"]
            }
          ]
        },
        {
          "requirement_name": "Managerial Economics",
          "critical": false,
          "credits": 3,
          "fulfilling_courses": [
            {
              "course_code": "BUS-G 304",
              "course_name": "MANAGERIAL ECONOMICS",
              "credits": 3,
              "scheduled_terms": ["Fall 2025", "Spring 2026"]
            }
          ]
        },
        {
          "requirement_name": "Fundamentals of Econ for Bus II",
          "critical": true,
          "minimum_grade": "C",
          "credits": 3,
          "fulfilling_courses": [
            {
              "course_code": "ECON-B 252",
              "course_name": "FUNDAMENTALS OF ECONOMICS FOR BUSINESS II",
              "credits": 3,
              "scheduled_terms": ["Fall 2025", "Spring 2026", "Summer 2026"]
            }
          ]
        },
        {
          "requirement_name": "Introduction to Business Ethics",
          "critical": false,
          "credits": 3,
          "fulfilling_courses": [
            {
              "course_code": "BUS-L 375",
              "course_name": "INTRODUCTION TO BUSINESS ETHICS",
              "credits": 3,
              "scheduled_terms": ["Fall 2025", "Spring 2026", "Summer 2026"]
            },
            {
              "course_code": "BUS-L 376",
              "course_name": "INTRODUCTION TO BUSINESS ETHICS HONORS",
              "credits": 3,
              "scheduled_terms": ["Fall 2025", "Spring 2026"]
            }
          ]
        },
        {
          "requirement_name": "IUB GenEd Natural & Mathematical Sciences",
          "critical": false,
          "credits": 3,
          "fulfilling_courses": [],
          "note": "Many courses available - to be populated later"
        }
      ]
    }
  }
}

